{
  "type": "FeatureCollection",
  "features": [
    {
      "type": "Feature",
      "geometry": {
        "type": "MultiPolygon",
        "coordinates": [
          [
            [
              [
                60.476718902587891,
                44.488056182861385
              ],
              [
                60.375473022460881,
                44.549922943115178
              ],
              [
                60.34244537353527,
                44.569850921630916
              ],
              [
                60.108322143554688,
                44.715915679931641
              ],
              [
                60.000339508056697,
                44.78807449340826
              ],
              [
                59.927787780761832,
                44.837409973144645
              ],
              [
                59.878131866455021,
                44.868118286132926
              ],
              [
                59.792713165283203,
                44.923030853271484
              ],
              [
                59.731914520263672,
                44.958377838134822
              ],
              [
                59.639915466308651,
                45.011863708496151
              ],
              [
                59.576301574706974,
                45.046321868896541
              ],
              [
                59.457550048828182,
                45.113582611083984
              ],
              [
                59.409816741943416,
                45.137916564941406
              ],
              [
                59.40958404541027,
                45.137916564941406
              ],
              [
                59.40958404541027,
                45.137359619140625
              ],
              [
                59.409305572509709,
                45.137359619140625
              ],
              [
                59.409305572509709,
                45.136528015136662
              ],
              [
                59.409027099609318,
                45.136528015136662
              ],
              [
                59.409027099609318,
                45.135971069335938
              ],
              [
                59.408748626708928,
                45.135971069335938
              ],
              [
                59.408748626708928,
                45.135417938232479
              ],
              [
                59.408473968505916,
                45.135341644287109
              ],
              [
                59.408298492431697,
                45.135429382324219
              ],
              [
                59.302341461181641,
                45.189537048339957
              ],
              [
                59.202846527099666,
                45.242835998535156
              ],
              [
                59.152534484863281,
                45.268486022949332
              ],
              [
                59.109111785888672,
                45.290622711181697
              ],
              [
                59.055515289306641,
                45.317947387695312
              ],
              [
                59.017822265624943,
                45.984935760498104
              ],
              [
                59.290802001953125,
                46.218589782714844
              ],
              [
                59.510917663574219,
                46.447574615478516
              ],
              [
                59.626117706298885,
                46.534854888916129
              ],
              [
                59.710865020751896,
                46.625709533691463
              ],
              [
                60.114334106445426,
                46.883270263671989
              ],
              [
                60.421405792236328,
                46.900722503662223
              ],
              [
                60.45006179809576,
                47.11773681640625
              ],
              [
                60.869571685790959,
                47.09405517578125
              ],
              [
                61.214015960693473,
                47.720077514648438
              ],
              [
                61.822719573974609,
                47.814785003662109
              ],
              [
                61.994113922119254,
                47.640701293945312
              ],
              [
                62.076602935791016,
                47.534423828125114
              ],
              [
                62.201557159423885,
                47.547328948974553
              ],
              [
                62.478031158447379,
                47.308898925781307
              ],
              [
                62.434638977050895,
                47.240909576416072
              ],
              [
                62.722553253173942,
                47.210189819336051
              ],
              [
                62.766426086425838,
                47.167449951171989
              ],
              [
                62.842063903808537,
                47.183910369873104
              ],
              [
                62.566246032714957,
                47.03660964965826
              ],
              [
                62.399642944335994,
                46.900733947753963
              ],
              [
                62.338962554931754,
                46.785942077636776
              ],
              [
                62.217311859130803,
                46.671051025390625
              ],
              [
                62.082290649414119,
                46.356182098388615
              ],
              [
                62.108539581298942,
                46.267002105712947
              ],
              [
                62.002624511718864,
                46.139137268066463
              ],
              [
                61.911148071289062,
                45.972965240478629
              ],
              [
                61.836475372314453,
                45.879039764404354
              ],
              [
                61.836936950683594,
                45.866291046142635
              ],
              [
                61.878623962402457,
                45.870792388916016
              ],
              [
                61.897453308105526,
                45.845397949218807
              ],
              [
                61.821086883544979,
                45.810939788818359
              ],
              [
                61.778217315673942,
                45.840408325195312
              ],
              [
                61.738555908203182,
                45.789154052734432
              ],
              [
                61.719501495361271,
                45.818767547607479
              ],
              [
                61.685783386230582,
                45.771804809570369
              ],
              [
                61.67246246337902,
                45.805698394775504
              ],
              [
                61.631633758544922,
                45.788417816162109
              ],
              [
                61.623306274414062,
                45.843582153320256
              ],
              [
                61.580436706543026,
                45.873001098632812
              ],
              [
                61.553031921386832,
                45.82182693481451
              ],
              [
                61.511371612548942,
                45.825759887695369
              ],
              [
                61.492225646972599,
                45.855339050293026
              ],
              [
                61.475868225097656,
                45.825485229492188
              ],
              [
                61.351245880126953,
                45.837219238281307
              ],
              [
                61.363140106201229,
                45.722705841064567
              ],
              [
                61.287376403808537,
                45.713588714599723
              ],
              [
                61.282974243164176,
                45.688091278076172
              ],
              [
                61.279346466064453,
                45.649875640869254
              ],
              [
                61.348289489746094,
                45.569831848144645
              ],
              [
                61.377006530761832,
                45.578540802002067
              ],
              [
                61.379959106445312,
                45.527660369873047
              ],
              [
                61.328010559081974,
                45.518768310546818
              ],
              [
                61.292057037353459,
                45.535442352295036
              ],
              [
                61.270130157470646,
                45.514053344726562
              ],
              [
                61.241065979003906,
                45.513813018798885
              ],
              [
                61.265380859375057,
                45.497051239013729
              ],
              [
                61.254550933837891,
                45.48424148559576
              ],
              [
                61.256145477295036,
                45.458812713623047
              ],
              [
                61.284408569335994,
                45.471763610839901
              ],
              [
                61.29682540893549,
                45.459144592285213
              ],
              [
                61.263290405273494,
                45.437671661376953
              ],
              [
                61.276248931884766,
                45.416580200195312
              ],
              [
                61.322463989257926,
                45.421188354492244
              ],
              [
                61.340690612793026,
                45.408611297607365
              ],
              [
                61.31298828125,
                45.387195587158317
              ],
              [
                61.338901519775447,
                45.345005035400447
              ],
              [
                61.354713439941349,
                45.370559692382756
              ],
              [
                61.363475799560604,
                45.323997497558707
              ],
              [
                61.391693115234489,
                45.336921691894588
              ],
              [
                61.422592163086051,
                45.307472229003906
              ],
              [
                61.401275634765625,
                45.277652740478572
              ],
              [
                61.419494628906307,
                45.265068054199332
              ],
              [
                61.446605682373047,
                45.294925689697379
              ],
              [
                61.471153259277401,
                45.273902893066406
              ],
              [
                61.453933715820312,
                45.180557250976676
              ],
              [
                61.472152709961051,
                45.167968750000114
              ],
              [
                61.470176696777344,
                45.108650207519645
              ],
              [
                60.648284912109375,
                44.382507324218864
              ],
              [
                60.558441162109375,
                44.438121795654411
              ],
              [
                60.476718902587891,
                44.488056182861385
              ]
            ]
          ]
        ]
      },
      "properties": {
        "name": "Aralskiy",
        "id": "Aralskiy",
        "datastat": "0/0/0",
        "dataImg": [
          "http://localhost:63342/map/green.svg?_ijt=d277mp04sbfulu08g6qou6kdag",
          "http://localhost:63342/map/red.svg?_ijt=d277mp04sbfulu08g6qou6kdag",
          "http://localhost:63342/map/yellow.svg?_ijt=d277mp04sbfulu08g6qou6kdag"
        ]
      }
    },
    {
      "type": "Feature",
      "geometry": {
        "type": "MultiPolygon",
        "coordinates": [
          [
            [
              [
                63.37785720825201,
                43.672752380371151
              ],
              [
                63.372066497802734,
                43.671695709228572
              ],
              [
                63.368274688720703,
                43.671619415283203
              ],
              [
                63.247856140136776,
                43.657131195068359
              ],
              [
                63.208065032959041,
                43.652492523193473
              ],
              [
                63.113143920898438,
                43.640308380126896
              ],
              [
                63.091438293457088,
                43.636772155761832
              ],
              [
                62.998729705810661,
                43.624336242675895
              ],
              [
                62.983161926269645,
                43.622238159179801
              ],
              [
                62.938945770263729,
                43.61674880981451
              ],
              [
                62.900367736816463,
                43.610580444335994
              ],
              [
                62.801742553710994,
                43.597366333007812
              ],
              [
                62.736175537109489,
                43.587734222412109
              ],
              [
                62.644615173339957,
                43.575283050537109
              ],
              [
                62.604553222656364,
                43.569526672363338
              ],
              [
                62.585128784179801,
                43.566276550292969
              ],
              [
                62.489490509033146,
                43.55291748046875
              ],
              [
                62.477382659912166,
                43.550563812255916
              ],
              [
                62.430381774902401,
                43.544055938720703
              ],
              [
                62.414215087890739,
                43.542278289794865
              ],
              [
                62.410404205322266,
                43.541709899902401
              ],
              [
                62.338951110839844,
                43.531356811523438
              ],
              [
                62.321792602539062,
                43.528678894042969
              ],
              [
                62.297245025634766,
                43.525215148925781
              ],
              [
                62.288471221923828,
                43.523975372314453
              ],
              [
                62.224391937255859,
                43.515155792236442
              ],
              [
                62.183765411376953,
                43.509044647216911
              ],
              [
                62.134605407714957,
                43.502017974853629
              ],
              [
                62.028697967529297,
                43.486515045166072
              ],
              [
                62.027404785156364,
                43.486602783203182
              ],
              [
                62.022636413574332,
                43.486923217773438
              ],
              [
                62.010833740234318,
                43.487712860107536
              ],
              [
                61.999526977539119,
                43.493984222412223
              ],
              [
                61.989238739013672,
                43.501831054687557
              ],
              [
                61.975631713867244,
                43.512290954589844
              ],
              [
                61.92442703247076,
                43.558448791503906
              ],
              [
                61.989055633544922,
                43.579437255859375
              ],
              [
                61.997306823730412,
                43.621387481689567
              ],
              [
                62.044342041015682,
                43.608730316162166
              ],
              [
                62.144889831543082,
                43.641944885253906
              ],
              [
                62.282176971435547,
                43.797012329101562
              ],
              [
                62.339576721191463,
                43.792549133300838
              ],
              [
                62.406723022460994,
                43.893482208251953
              ],
              [
                62.474586486816406,
                44.150886535644588
              ],
              [
                62.637447357177848,
                44.493480682373047
              ],
              [
                62.697875976562443,
                44.565509796142692
              ],
              [
                62.845851898193359,
                44.828369140625
              ],
              [
                62.830795288086051,
                44.934436798095817
              ],
              [
                62.857601165771428,
                45.303485870361442
              ],
              [
                62.899257659912109,
                45.316131591796932
              ],
              [
                63.088989257812557,
                45.510787963867188
              ],
              [
                62.936595916748047,
                45.655498504638729
              ],
              [
                62.952873229980412,
                45.876140594482422
              ],
              [
                63.03167724609375,
                45.935317993164176
              ],
              [
                63.086566925048885,
                46.087799072265682
              ],
              [
                63.198348999023381,
                46.239669799804744
              ],
              [
                63.167503356933594,
                46.261093139648551
              ],
              [
                63.230033874511719,
                46.315685272216854
              ],
              [
                63.150714874267692,
                46.502811431884879
              ],
              [
                63.140598297119197,
                46.748733520507869
              ],
              [
                63.099399566650447,
                47.011970520019645
              ],
              [
                63.250316619873161,
                46.942577362060604
              ],
              [
                63.383609771728629,
                46.949520111084098
              ],
              [
                63.680282592773494,
                46.835578918457145
              ],
              [
                63.777130126953182,
                46.876495361328182
              ],
              [
                63.821067810058707,
                46.84622955322277
              ],
              [
                63.781917572021428,
                46.817203521728516
              ],
              [
                63.7978515625,
                46.698532104492244
              ],
              [
                63.972957611084041,
                46.37042236328125
              ],
              [
                64.147254943847599,
                46.257926940917969
              ],
              [
                64.378128051757869,
                45.967105865478516
              ],
              [
                64.349899291992244,
                45.722686767578125
              ],
              [
                64.423133850097656,
                45.493587493896541
              ],
              [
                64.460479736328125,
                45.319931030273494
              ],
              [
                64.354469299316406,
                45.321468353271484
              ],
              [
                64.365493774414062,
                45.279075622558594
              ],
              [
                64.413223266601619,
                45.219272613525391
              ],
              [
                64.341987609863395,
                45.127326965332145
              ],
              [
                64.35369873046875,
                45.106044769287166
              ],
              [
                64.297760009765568,
                45.094104766845703
              ],
              [
                64.272529602050895,
                45.073295593261776
              ],
              [
                64.296218872070256,
                45.039184570312557
              ],
              [
                64.115905761718807,
                44.914463043212891
              ],
              [
                64.060478210449162,
                44.864280700683651
              ],
              [
                63.945442199707145,
                44.840019226074276
              ],
              [
                63.915348052978572,
                44.840290069580078
              ],
              [
                63.897441864013786,
                44.865867614746207
              ],
              [
                63.795372009277344,
                44.837013244628963
              ],
              [
                63.729496002197266,
                44.884117126464901
              ],
              [
                63.615898132324219,
                44.901790618896598
              ],
              [
                63.556518554687614,
                44.863960266113395
              ],
              [
                63.511661529541016,
                44.639366149902401
              ],
              [
                63.513702392578125,
                44.51629638671875
              ],
              [
                63.503940582275447,
                44.414482116699276
              ],
              [
                63.427726745605526,
                44.198345184326286
              ],
              [
                63.421283721923828,
                44.041248321533203
              ],
              [
                63.385650634765568,
                43.918277740478516
              ],
              [
                63.402065277099666,
                43.799324035644531
              ],
              [
                63.37785720825201,
                43.672752380371151
              ]
            ]
          ]
        ]
      },
      "properties": {
        "name": "Karmakchinskiy",
        "id": "Karmakchinskiy",
        "datastat": "0/0/0",
        "dataImg": [
          "http://localhost:63342/map/green.svg?_ijt=d277mp04sbfulu08g6qou6kdag",
          "http://localhost:63342/map/red.svg?_ijt=d277mp04sbfulu08g6qou6kdag",
          "http://localhost:63342/map/yellow.svg?_ijt=d277mp04sbfulu08g6qou6kdag"
        ]
      }
    },
    {
      "type": "Feature",
      "geometry": {
        "type": "MultiPolygon",
        "coordinates": [
          [
            [
              [
                61.92442703247076,
                43.558448791503906
              ],
              [
                61.832290649414176,
                43.641502380371207
              ],
              [
                61.790027618408317,
                43.679725646972656
              ],
              [
                61.718318939209098,
                43.743400573730412
              ],
              [
                61.705280303955135,
                43.754978179931641
              ],
              [
                61.676227569580078,
                43.781826019287223
              ],
              [
                61.620388031005916,
                43.83154296875
              ],
              [
                61.611629486084041,
                43.840461730957145
              ],
              [
                61.61143875122076,
                43.840618133544922
              ],
              [
                61.588150024414176,
                43.859588623046875
              ],
              [
                61.526695251464901,
                43.914432525634766
              ],
              [
                61.489231109619254,
                43.948066711425724
              ],
              [
                61.488372802734489,
                43.950145721435604
              ],
              [
                61.478527069091854,
                43.956790924072266
              ],
              [
                61.474018096923771,
                43.962394714355469
              ],
              [
                61.433692932128906,
                43.997219085693359
              ],
              [
                61.419822692871094,
                44.0064697265625
              ],
              [
                61.419860839843807,
                44.007381439209041
              ],
              [
                61.413593292236328,
                44.016460418701172
              ],
              [
                61.323238372802791,
                44.094051361084098
              ],
              [
                61.275432586670036,
                44.136764526367188
              ],
              [
                61.252754211425838,
                44.134845733642692
              ],
              [
                61.262294769287053,
                44.119945526123104
              ],
              [
                61.244827270507926,
                44.134174346923828
              ],
              [
                61.160774230957031,
                44.127067565918026
              ],
              [
                61.153511047363281,
                44.127639770507869
              ],
              [
                61.037162780761719,
                44.136825561523494
              ],
              [
                61.036132812500114,
                44.13707351684576
              ],
              [
                60.920223236084041,
                44.209384918212947
              ],
              [
                60.871902465820369,
                44.242198944091854
              ],
              [
                60.840675354003849,
                44.263404846191406
              ],
              [
                60.653953552246037,
                44.378997802734375
              ],
              [
                60.648284912109375,
                44.382507324218864
              ],
              [
                61.470176696777344,
                45.108650207519645
              ],
              [
                61.472152709961051,
                45.167968750000114
              ],
              [
                61.453933715820312,
                45.180557250976676
              ],
              [
                61.471153259277401,
                45.273902893066406
              ],
              [
                61.446605682373047,
                45.294925689697379
              ],
              [
                61.419494628906307,
                45.265068054199332
              ],
              [
                61.401275634765625,
                45.277652740478572
              ],
              [
                61.422592163086051,
                45.307472229003906
              ],
              [
                61.391693115234489,
                45.336921691894588
              ],
              [
                61.363475799560604,
                45.323997497558707
              ],
              [
                61.354713439941349,
                45.370559692382756
              ],
              [
                61.338901519775447,
                45.345005035400447
              ],
              [
                61.31298828125,
                45.387195587158317
              ],
              [
                61.340690612793026,
                45.408611297607365
              ],
              [
                61.322463989257926,
                45.421188354492244
              ],
              [
                61.276248931884766,
                45.416580200195312
              ],
              [
                61.263290405273494,
                45.437671661376953
              ],
              [
                61.29682540893549,
                45.459144592285213
              ],
              [
                61.284408569335994,
                45.471763610839901
              ],
              [
                61.256145477295036,
                45.458812713623047
              ],
              [
                61.254550933837891,
                45.48424148559576
              ],
              [
                61.265380859375057,
                45.497051239013729
              ],
              [
                61.241065979003906,
                45.513813018798885
              ],
              [
                61.270130157470646,
                45.514053344726562
              ],
              [
                61.292057037353459,
                45.535442352295036
              ],
              [
                61.328010559081974,
                45.518768310546818
              ],
              [
                61.379959106445312,
                45.527660369873047
              ],
              [
                61.377006530761832,
                45.578540802002067
              ],
              [
                61.348289489746094,
                45.569831848144645
              ],
              [
                61.279346466064453,
                45.649875640869254
              ],
              [
                61.282974243164176,
                45.688091278076172
              ],
              [
                61.287376403808537,
                45.713588714599723
              ],
              [
                61.363140106201229,
                45.722705841064567
              ],
              [
                61.351245880126953,
                45.837219238281307
              ],
              [
                61.475868225097656,
                45.825485229492188
              ],
              [
                61.492225646972599,
                45.855339050293026
              ],
              [
                61.511371612548942,
                45.825759887695369
              ],
              [
                61.553031921386832,
                45.82182693481451
              ],
              [
                61.580436706543026,
                45.873001098632812
              ],
              [
                61.623306274414062,
                45.843582153320256
              ],
              [
                61.631633758544922,
                45.788417816162109
              ],
              [
                61.67246246337902,
                45.805698394775504
              ],
              [
                61.685783386230582,
                45.771804809570369
              ],
              [
                61.719501495361271,
                45.818767547607479
              ],
              [
                61.738555908203182,
                45.789154052734432
              ],
              [
                61.778217315673942,
                45.840408325195312
              ],
              [
                61.821086883544979,
                45.810939788818359
              ],
              [
                61.897453308105526,
                45.845397949218807
              ],
              [
                61.878623962402457,
                45.870792388916016
              ],
              [
                61.836936950683594,
                45.866291046142635
              ],
              [
                61.836475372314453,
                45.879039764404354
              ],
              [
                61.911148071289062,
                45.972965240478629
              ],
              [
                62.002624511718864,
                46.139137268066463
              ],
              [
                62.108539581298942,
                46.267002105712947
              ],
              [
                62.082290649414119,
                46.356182098388615
              ],
              [
                62.217311859130803,
                46.671051025390625
              ],
              [
                62.338962554931754,
                46.785942077636776
              ],
              [
                62.399642944335994,
                46.900733947753963
              ],
              [
                62.566246032714957,
                47.03660964965826
              ],
              [
                62.980167388916072,
                47.089424133300895
              ],
              [
                63.099399566650447,
                47.011970520019645
              ],
              [
                63.140598297119197,
                46.748733520507869
              ],
              [
                63.150714874267692,
                46.502811431884879
              ],
              [
                63.230033874511719,
                46.315685272216854
              ],
              [
                63.167503356933594,
                46.261093139648551
              ],
              [
                63.198348999023381,
                46.239669799804744
              ],
              [
                63.086566925048885,
                46.087799072265682
              ],
              [
                63.03167724609375,
                45.935317993164176
              ],
              [
                62.952873229980412,
                45.876140594482422
              ],
              [
                62.936595916748047,
                45.655498504638729
              ],
              [
                63.088989257812557,
                45.510787963867188
              ],
              [
                62.899257659912109,
                45.316131591796932
              ],
              [
                62.857601165771428,
                45.303485870361442
              ],
              [
                62.830795288086051,
                44.934436798095817
              ],
              [
                62.845851898193359,
                44.828369140625
              ],
              [
                62.697875976562443,
                44.565509796142692
              ],
              [
                62.637447357177848,
                44.493480682373047
              ],
              [
                62.474586486816406,
                44.150886535644588
              ],
              [
                62.406723022460994,
                43.893482208251953
              ],
              [
                62.339576721191463,
                43.792549133300838
              ],
              [
                62.282176971435547,
                43.797012329101562
              ],
              [
                62.144889831543082,
                43.641944885253906
              ],
              [
                62.044342041015682,
                43.608730316162166
              ],
              [
                61.997306823730412,
                43.621387481689567
              ],
              [
                61.989055633544922,
                43.579437255859375
              ],
              [
                61.92442703247076,
                43.558448791503906
              ]
            ]
          ]
        ]
      },
      "properties": {
        "name": "Kazalinskiy",
        "id": "Kazalinskiy",
        "datastat": "0/0/0",
        "dataImg": [
          "http://localhost:63342/map/green.svg?_ijt=d277mp04sbfulu08g6qou6kdag",
          "http://localhost:63342/map/red.svg?_ijt=d277mp04sbfulu08g6qou6kdag",
          "http://localhost:63342/map/yellow.svg?_ijt=d277mp04sbfulu08g6qou6kdag"
        ]
      }
    },
    {
      "type": "Feature",
      "geometry": {
        "type": "MultiPolygon",
        "coordinates": [
          [
            [
              [
                65.755416870117244,
                44.637748718261832
              ],
              [
                65.712356567382869,
                44.625782012939567
              ],
              [
                65.671829223632812,
                44.660091400146541
              ],
              [
                65.557754516601562,
                44.682895660400391
              ],
              [
                65.542129516601562,
                44.615722656250057
              ],
              [
                65.437736511230582,
                44.591987609863224
              ],
              [
                65.414268493652457,
                44.60919189453125
              ],
              [
                65.445899963378963,
                44.634014129638786
              ],
              [
                65.367660522460994,
                44.652038574218864
              ],
              [
                65.329696655273438,
                44.749565124511719
              ],
              [
                65.343551635742131,
                44.783077239990291
              ],
              [
                65.295486450195256,
                44.800670623779354
              ],
              [
                65.308738708496151,
                44.821544647216797
              ],
              [
                65.278755187988281,
                44.834651947021598
              ],
              [
                65.241195678710938,
                44.818367004394645
              ],
              [
                65.223205566406193,
                44.827075958251953
              ],
              [
                65.28018951416027,
                44.864139556884822
              ],
              [
                65.263229370117301,
                44.89390945434576
              ],
              [
                65.299995422363338,
                44.893333435058707
              ],
              [
                65.338600158691349,
                44.930660247802734
              ],
              [
                65.195816040039119,
                45.025646209716797
              ],
              [
                65.21897125244152,
                45.122219085693416
              ],
              [
                65.118705749511719,
                45.22080230712902
              ],
              [
                65.216972351074219,
                45.332958221435547
              ],
              [
                65.359230041503906,
                45.334751129150504
              ],
              [
                65.524002075195312,
                45.302440643310547
              ],
              [
                65.452644348144474,
                45.236297607421875
              ],
              [
                65.434417724609432,
                45.240818023681641
              ],
              [
                65.414405822753963,
                45.211677551269474
              ],
              [
                65.377723693847656,
                45.216503143310661
              ],
              [
                65.377067565918082,
                45.203880310058594
              ],
              [
                65.4010009765625,
                45.190845489501953
              ],
              [
                65.362373352050838,
                45.157791137695369
              ],
              [
                65.36248779296875,
                45.039829254150447
              ],
              [
                65.400787353515625,
                45.068698883056754
              ],
              [
                65.456176757812557,
                45.072002410888672
              ],
              [
                65.472991943359432,
                45.042247772216797
              ],
              [
                65.547119140625,
                45.05366134643549
              ],
              [
                65.551391601562614,
                45.019908905029297
              ],
              [
                65.576316833496151,
                45.027919769287109
              ],
              [
                65.587379455566463,
                45.006687164306754
              ],
              [
                65.655059814453125,
                45.013984680175838
              ],
              [
                65.653388977050838,
                44.984550476074219
              ],
              [
                65.773948669433651,
                44.957294464111442
              ],
              [
                65.765869140625,
                44.923767089843807
              ],
              [
                65.734909057617301,
                44.915866851806697
              ],
              [
                65.745620727539006,
                44.890438079833984
              ],
              [
                65.702995300293026,
                44.891139984130973
              ],
              [
                65.719085693359489,
                44.852996826171932
              ],
              [
                65.676025390625,
                44.845275878906193
              ],
              [
                65.687240600586051,
                44.828254699707145
              ],
              [
                65.752418518066463,
                44.797744750976676
              ],
              [
                65.772605895996151,
                44.831085205078182
              ],
              [
                65.809829711914119,
                44.843097686767578
              ],
              [
                65.8896484375,
                44.854396820068359
              ],
              [
                65.905555725097713,
                44.816276550293082
              ],
              [
                65.861495971679744,
                44.791763305664119
              ],
              [
                65.884757995605526,
                44.774555206298942
              ],
              [
                65.864524841308651,
                44.741230010986271
              ],
              [
                65.930198669433707,
                44.723335266113338
              ],
              [
                65.864311218261719,
                44.636043548584041
              ],
              [
                65.763381958007812,
                44.671298980712891
              ],
              [
                65.755416870117244,
                44.637748718261832
              ]
            ]
          ]
        ]
      },
      "properties": {
        "name": "Qyzylorda",
        "id": "Qyzylorda",
        "datastat": "0/0/0",
        "dataImg": [
          "http://localhost:63342/map/green.svg?_ijt=d277mp04sbfulu08g6qou6kdag",
          "http://localhost:63342/map/red.svg?_ijt=d277mp04sbfulu08g6qou6kdag",
          "http://localhost:63342/map/yellow.svg?_ijt=d277mp04sbfulu08g6qou6kdag"
        ]
      }
    },
    {
      "type": "Feature",
      "geometry": {
        "type": "MultiPolygon",
        "coordinates": [
          [
            [
              [
                65.079246520996094,
                43.776645660400504
              ],
              [
                65.101669311523551,
                43.785545349121207
              ],
              [
                65.347831726074276,
                43.998233795166072
              ],
              [
                65.470840454101619,
                44.148643493652401
              ],
              [
                65.688316345214901,
                44.289146423339844
              ],
              [
                65.79010009765625,
                44.283500671386776
              ],
              [
                65.877593994140739,
                44.345413208007812
              ],
              [
                65.892013549804744,
                44.387298583984489
              ],
              [
                65.875427246093807,
                44.412803649902401
              ],
              [
                65.900711059570312,
                44.433471679687614
              ],
              [
                65.884613037109489,
                44.467388153076172
              ],
              [
                65.915718078613395,
                44.483749389648494
              ],
              [
                65.895828247070369,
                44.555595397949219
              ],
              [
                65.755416870117244,
                44.637748718261832
              ],
              [
                65.763381958007812,
                44.671298980712891
              ],
              [
                65.864311218261719,
                44.636043548584041
              ],
              [
                65.930198669433707,
                44.723335266113338
              ],
              [
                65.864524841308651,
                44.741230010986271
              ],
              [
                65.884757995605526,
                44.774555206298942
              ],
              [
                65.861495971679744,
                44.791763305664119
              ],
              [
                65.905555725097713,
                44.816276550293082
              ],
              [
                65.8896484375,
                44.854396820068359
              ],
              [
                66.032791137695369,
                44.994892120361442
              ],
              [
                65.997817993164062,
                45.02072906494152
              ],
              [
                66.13970947265625,
                45.127426147460938
              ],
              [
                66.157493591308651,
                45.118694305419865
              ],
              [
                66.248260498046875,
                45.188308715820369
              ],
              [
                66.399803161621207,
                45.084335327148438
              ],
              [
                66.571037292480526,
                45.088623046875114
              ],
              [
                66.875778198242188,
                45.603351593017521
              ],
              [
                67.236824035644531,
                45.59519195556652
              ],
              [
                67.329849243164176,
                45.541561126708928
              ],
              [
                67.320350646972656,
                45.437397003173942
              ],
              [
                67.256668090820312,
                45.272514343261832
              ],
              [
                67.447082519531307,
                45.160984039306754
              ],
              [
                67.606323242187557,
                45.112968444824276
              ],
              [
                67.612274169921932,
                44.411468505859432
              ],
              [
                67.592422485351619,
                44.391372680664062
              ],
              [
                67.53794097900402,
                44.385097503662223
              ],
              [
                67.492477416992244,
                44.411830902099553
              ],
              [
                67.471511840820369,
                44.379211425781307
              ],
              [
                67.399848937988395,
                44.381786346435604
              ],
              [
                67.344635009765682,
                44.300201416015625
              ],
              [
                67.206260681152287,
                44.292232513427848
              ],
              [
                67.041893005371094,
                44.188491821289119
              ],
              [
                66.936630249023438,
                44.069980621338004
              ],
              [
                66.856925964355526,
                43.967208862304744
              ],
              [
                66.869186401367301,
                43.89570236206049
              ],
              [
                66.805961608886719,
                43.846755981445426
              ],
              [
                66.797058105468807,
                43.729476928710881
              ],
              [
                66.773880004882812,
                43.41478347778326
              ],
              [
                66.392478942871151,
                43.310260772705135
              ],
              [
                66.425041198730469,
                43.267696380615291
              ],
              [
                66.514038085937614,
                42.870281219482536
              ],
              [
                66.103744506835994,
                42.625064849853516
              ],
              [
                66.10345458984375,
                42.66961669921875
              ],
              [
                66.103523254394588,
                42.688453674316349
              ],
              [
                66.103294372558594,
                42.701679229736442
              ],
              [
                66.101905822753849,
                42.78162765502924
              ],
              [
                66.101219177246151,
                42.880023956298942
              ],
              [
                66.100570678710881,
                42.934528350830135
              ],
              [
                66.099205017089957,
                42.962192535400504
              ],
              [
                66.017028808593693,
                42.9339599609375
              ],
              [
                65.999961853027401,
                42.928073883056754
              ],
              [
                65.916038513183651,
                42.899055480957031
              ],
              [
                65.827186584472713,
                42.868133544921875
              ],
              [
                65.822807312011832,
                42.877559661865178
              ],
              [
                65.814422607421989,
                42.895580291748104
              ],
              [
                65.806732177734432,
                42.915592193603572
              ],
              [
                65.791946411132926,
                42.950050354003963
              ],
              [
                65.769218444824332,
                43.002696990966797
              ],
              [
                65.763412475585938,
                43.020286560058707
              ],
              [
                65.740501403808594,
                43.074535369873161
              ],
              [
                65.722221374511719,
                43.117473602295036
              ],
              [
                65.709724426269645,
                43.148105621337947
              ],
              [
                65.695526123046932,
                43.180446624755803
              ],
              [
                65.683547973632869,
                43.207592010498047
              ],
              [
                65.673789978027401,
                43.236408233642635
              ],
              [
                65.651077270507812,
                43.303516387939453
              ],
              [
                65.560333251953182,
                43.363651275634822
              ],
              [
                65.490158081054744,
                43.409164428710994
              ],
              [
                65.446113586425895,
                43.438171386718864
              ],
              [
                65.415649414062443,
                43.456264495849609
              ],
              [
                65.337890625,
                43.515205383300838
              ],
              [
                65.310195922851562,
                43.533329010009766
              ],
              [
                65.296279907226562,
                43.54367828369152
              ],
              [
                65.294136047363395,
                43.545272827148438
              ],
              [
                65.27579498291027,
                43.574337005615234
              ],
              [
                65.274932861328125,
                43.578060150146541
              ],
              [
                65.267227172851676,
                43.588600158691463
              ],
              [
                65.255393981933707,
                43.607872009277401
              ],
              [
                65.255035400390739,
                43.610420227050895
              ],
              [
                65.25101470947277,
                43.617076873779297
              ],
              [
                65.246231079101676,
                43.622627258300895
              ],
              [
                65.207977294921875,
                43.681735992431641
              ],
              [
                65.199539184570256,
                43.694606781005916
              ],
              [
                65.188827514648551,
                43.712890624999943
              ],
              [
                65.184570312500057,
                43.723461151123161
              ],
              [
                65.183319091796989,
                43.723533630371207
              ],
              [
                65.170242309570312,
                43.743549346923828
              ],
              [
                65.148719787597713,
                43.76151275634777
              ],
              [
                65.132240295410156,
                43.770465850830135
              ],
              [
                65.114418029785213,
                43.775592803955078
              ],
              [
                65.079246520996094,
                43.776645660400504
              ]
            ]
          ]
        ]
      },
      "properties": {
        "name": "Shieliyskiy",
        "id": "Shieliyskiy",
        "datastat": "0/0/0",
        "dataImg": [
          "http://localhost:63342/map/green.svg?_ijt=d277mp04sbfulu08g6qou6kdag",
          "http://localhost:63342/map/red.svg?_ijt=d277mp04sbfulu08g6qou6kdag",
          "http://localhost:63342/map/yellow.svg?_ijt=d277mp04sbfulu08g6qou6kdag"
        ]
      }
    },
    {
      "type": "Feature",
      "geometry": {
        "type": "MultiPolygon",
        "coordinates": [
          [
            [
              [
                65.079246520996094,
                43.776645660400504
              ],
              [
                65.078102111816406,
                43.776679992675838
              ],
              [
                65.054801940917969,
                43.774978637695369
              ],
              [
                65.010261535644588,
                43.766853332519645
              ],
              [
                64.965240478515682,
                43.750938415527401
              ],
              [
                64.956390380859375,
                43.74797439575201
              ],
              [
                64.950202941894645,
                43.746242523193416
              ],
              [
                64.947090148925838,
                43.743659973144531
              ],
              [
                64.915565490722656,
                43.732501983642578
              ],
              [
                64.905441284179631,
                43.729373931884879
              ],
              [
                64.779243469238338,
                43.688564300537053
              ],
              [
                64.763984680175838,
                43.684547424316463
              ],
              [
                64.718994140625057,
                43.668365478515682
              ],
              [
                64.671112060546932,
                44.2689208984375
              ],
              [
                64.737564086914176,
                44.454250335693416
              ],
              [
                64.72772216796875,
                44.682601928710938
              ],
              [
                64.679435729980469,
                44.708625793457088
              ],
              [
                64.670509338378906,
                44.797470092773438
              ],
              [
                64.609130859375057,
                44.806789398193473
              ],
              [
                64.609909057617244,
                44.827903747558707
              ],
              [
                64.741539001464957,
                44.868232727050781
              ],
              [
                64.847862243652344,
                44.879287719726562
              ],
              [
                64.880867004394531,
                44.916748046875114
              ],
              [
                64.763679504394645,
                44.948104858398438
              ],
              [
                64.771423339843807,
                44.981746673583928
              ],
              [
                64.847389221191463,
                45.001651763916016
              ],
              [
                64.799697875976619,
                45.053043365478629
              ],
              [
                64.824943542480412,
                45.056858062744254
              ],
              [
                64.808128356933707,
                45.099315643310604
              ],
              [
                64.833961486816406,
                45.115776062011719
              ],
              [
                64.761077880859375,
                45.16757965087902
              ],
              [
                64.752006530761776,
                45.243667602539176
              ],
              [
                64.785324096679688,
                45.285308837890568
              ],
              [
                64.768020629882869,
                45.319339752197379
              ],
              [
                64.839401245117301,
                45.790512084961051
              ],
              [
                64.859970092773494,
                45.82810211181652
              ],
              [
                64.879287719726676,
                45.975334167480582
              ],
              [
                64.887451171875114,
                46.152263641357536
              ],
              [
                64.854080200195426,
                46.389003753662109
              ],
              [
                64.930221557617131,
                46.522457122802848
              ],
              [
                65.139076232910099,
                46.509876251220817
              ],
              [
                65.321281433105469,
                46.367179870605469
              ],
              [
                65.506416320800895,
                46.296031951904354
              ],
              [
                66.814384460449276,
                46.049259185791129
              ],
              [
                67.143356323242188,
                46.06308746337902
              ],
              [
                67.211433410644531,
                46.064769744873047
              ],
              [
                67.259880065917969,
                46.054576873779411
              ],
              [
                67.275741577148438,
                45.957717895507869
              ],
              [
                67.262039184570369,
                45.874542236328125
              ],
              [
                67.420036315918082,
                45.788993835449332
              ],
              [
                67.450469970703125,
                45.720886230468864
              ],
              [
                67.421783447265739,
                45.676013946533317
              ],
              [
                67.361106872558707,
                45.61563873291027
              ],
              [
                67.329849243164176,
                45.541561126708928
              ],
              [
                67.236824035644531,
                45.59519195556652
              ],
              [
                66.875778198242188,
                45.603351593017521
              ],
              [
                66.571037292480526,
                45.088623046875114
              ],
              [
                66.399803161621207,
                45.084335327148438
              ],
              [
                66.248260498046875,
                45.188308715820369
              ],
              [
                66.157493591308651,
                45.118694305419865
              ],
              [
                66.13970947265625,
                45.127426147460938
              ],
              [
                65.997817993164062,
                45.02072906494152
              ],
              [
                66.032791137695369,
                44.994892120361442
              ],
              [
                65.8896484375,
                44.854396820068359
              ],
              [
                65.809829711914119,
                44.843097686767578
              ],
              [
                65.772605895996151,
                44.831085205078182
              ],
              [
                65.752418518066463,
                44.797744750976676
              ],
              [
                65.687240600586051,
                44.828254699707145
              ],
              [
                65.676025390625,
                44.845275878906193
              ],
              [
                65.719085693359489,
                44.852996826171932
              ],
              [
                65.702995300293026,
                44.891139984130973
              ],
              [
                65.745620727539006,
                44.890438079833984
              ],
              [
                65.734909057617301,
                44.915866851806697
              ],
              [
                65.765869140625,
                44.923767089843807
              ],
              [
                65.773948669433651,
                44.957294464111442
              ],
              [
                65.653388977050838,
                44.984550476074219
              ],
              [
                65.655059814453125,
                45.013984680175838
              ],
              [
                65.587379455566463,
                45.006687164306754
              ],
              [
                65.576316833496151,
                45.027919769287109
              ],
              [
                65.551391601562614,
                45.019908905029297
              ],
              [
                65.547119140625,
                45.05366134643549
              ],
              [
                65.472991943359432,
                45.042247772216797
              ],
              [
                65.456176757812557,
                45.072002410888672
              ],
              [
                65.400787353515625,
                45.068698883056754
              ],
              [
                65.36248779296875,
                45.039829254150447
              ],
              [
                65.362373352050838,
                45.157791137695369
              ],
              [
                65.4010009765625,
                45.190845489501953
              ],
              [
                65.377067565918082,
                45.203880310058594
              ],
              [
                65.377723693847656,
                45.216503143310661
              ],
              [
                65.414405822753963,
                45.211677551269474
              ],
              [
                65.434417724609432,
                45.240818023681641
              ],
              [
                65.452644348144474,
                45.236297607421875
              ],
              [
                65.524002075195312,
                45.302440643310547
              ],
              [
                65.359230041503906,
                45.334751129150504
              ],
              [
                65.216972351074219,
                45.332958221435547
              ],
              [
                65.118705749511719,
                45.22080230712902
              ],
              [
                65.21897125244152,
                45.122219085693416
              ],
              [
                65.195816040039119,
                45.025646209716797
              ],
              [
                65.338600158691349,
                44.930660247802734
              ],
              [
                65.299995422363338,
                44.893333435058707
              ],
              [
                65.263229370117301,
                44.89390945434576
              ],
              [
                65.28018951416027,
                44.864139556884822
              ],
              [
                65.223205566406193,
                44.827075958251953
              ],
              [
                65.241195678710938,
                44.818367004394645
              ],
              [
                65.278755187988281,
                44.834651947021598
              ],
              [
                65.308738708496151,
                44.821544647216797
              ],
              [
                65.295486450195256,
                44.800670623779354
              ],
              [
                65.343551635742131,
                44.783077239990291
              ],
              [
                65.329696655273438,
                44.749565124511719
              ],
              [
                65.367660522460994,
                44.652038574218864
              ],
              [
                65.445899963378963,
                44.634014129638786
              ],
              [
                65.414268493652457,
                44.60919189453125
              ],
              [
                65.437736511230582,
                44.591987609863224
              ],
              [
                65.542129516601562,
                44.615722656250057
              ],
              [
                65.557754516601562,
                44.682895660400391
              ],
              [
                65.671829223632812,
                44.660091400146541
              ],
              [
                65.712356567382869,
                44.625782012939567
              ],
              [
                65.755416870117244,
                44.637748718261832
              ],
              [
                65.895828247070369,
                44.555595397949219
              ],
              [
                65.915718078613395,
                44.483749389648494
              ],
              [
                65.884613037109489,
                44.467388153076172
              ],
              [
                65.900711059570312,
                44.433471679687614
              ],
              [
                65.875427246093807,
                44.412803649902401
              ],
              [
                65.892013549804744,
                44.387298583984489
              ],
              [
                65.877593994140739,
                44.345413208007812
              ],
              [
                65.79010009765625,
                44.283500671386776
              ],
              [
                65.688316345214901,
                44.289146423339844
              ],
              [
                65.470840454101619,
                44.148643493652401
              ],
              [
                65.347831726074276,
                43.998233795166072
              ],
              [
                65.101669311523551,
                43.785545349121207
              ],
              [
                65.079246520996094,
                43.776645660400504
              ]
            ]
          ]
        ]
      },
      "properties": {
        "name": "Terenozekskiy",
        "id": "Terenozekskiy",
        "datastat": "0/0/0",
        "dataImg": [
          "http://localhost:63342/map/green.svg?_ijt=d277mp04sbfulu08g6qou6kdag",
          "http://localhost:63342/map/red.svg?_ijt=d277mp04sbfulu08g6qou6kdag",
          "http://localhost:63342/map/yellow.svg?_ijt=d277mp04sbfulu08g6qou6kdag"
        ]
      }
    },
    {
      "type": "Feature",
      "geometry": {
        "type": "MultiPolygon",
        "coordinates": [
          [
            [
              [
                64.638916015625057,
                43.639690399170036
              ],
              [
                64.633949279785213,
                43.637825012207088
              ],
              [
                64.622467041015682,
                43.633365631103572
              ],
              [
                64.581619262695312,
                43.619159698486328
              ],
              [
                64.53653717041027,
                43.603313446044865
              ],
              [
                64.527320861816463,
                43.602634429931697
              ],
              [
                64.525077819824332,
                43.602287292480469
              ],
              [
                64.518165588378963,
                43.602634429931697
              ],
              [
                64.513847351074162,
                43.60033035278326
              ],
              [
                64.481193542480582,
                43.602195739746151
              ],
              [
                64.466987609863281,
                43.602214813232422
              ],
              [
                64.372962951660156,
                43.605953216552848
              ],
              [
                64.361900329589844,
                43.605808258056641
              ],
              [
                64.344978332519588,
                43.607089996338004
              ],
              [
                64.324134826660156,
                43.606960296630859
              ],
              [
                64.316566467285213,
                43.607097625732536
              ],
              [
                64.312507629394531,
                43.607524871826172
              ],
              [
                64.308464050292969,
                43.608180999755916
              ],
              [
                64.218750000000114,
                43.610889434814567
              ],
              [
                64.203117370605582,
                43.612548828125114
              ],
              [
                64.172241210937443,
                43.613098144531364
              ],
              [
                64.159156799316406,
                43.615093231201286
              ],
              [
                64.148117065429744,
                43.615154266357422
              ],
              [
                64.053871154785156,
                43.6202392578125
              ],
              [
                64.040084838867188,
                43.621330261230412
              ],
              [
                63.993629455566463,
                43.624382019042912
              ],
              [
                63.911880493164176,
                43.628086090088004
              ],
              [
                63.860027313232479,
                43.634536743164062
              ],
              [
                63.731739044189396,
                43.640628814697322
              ],
              [
                63.605957031249943,
                43.650596618652401
              ],
              [
                63.583061218261662,
                43.652477264404411
              ],
              [
                63.521862030029354,
                43.657100677490178
              ],
              [
                63.456634521484375,
                43.662765502929688
              ],
              [
                63.388889312744197,
                43.672855377197322
              ],
              [
                63.381351470947379,
                43.67338943481451
              ],
              [
                63.37785720825201,
                43.672752380371151
              ],
              [
                63.402065277099666,
                43.799324035644531
              ],
              [
                63.385650634765568,
                43.918277740478516
              ],
              [
                63.421283721923828,
                44.041248321533203
              ],
              [
                63.427726745605526,
                44.198345184326286
              ],
              [
                63.503940582275447,
                44.414482116699276
              ],
              [
                63.513702392578125,
                44.51629638671875
              ],
              [
                63.511661529541016,
                44.639366149902401
              ],
              [
                63.556518554687614,
                44.863960266113395
              ],
              [
                63.615898132324219,
                44.901790618896598
              ],
              [
                63.729496002197266,
                44.884117126464901
              ],
              [
                63.795372009277344,
                44.837013244628963
              ],
              [
                63.897441864013786,
                44.865867614746207
              ],
              [
                63.915348052978572,
                44.840290069580078
              ],
              [
                63.945442199707145,
                44.840019226074276
              ],
              [
                64.060478210449162,
                44.864280700683651
              ],
              [
                64.115905761718807,
                44.914463043212891
              ],
              [
                64.296218872070256,
                45.039184570312557
              ],
              [
                64.272529602050895,
                45.073295593261776
              ],
              [
                64.297760009765568,
                45.094104766845703
              ],
              [
                64.35369873046875,
                45.106044769287166
              ],
              [
                64.341987609863395,
                45.127326965332145
              ],
              [
                64.413223266601619,
                45.219272613525391
              ],
              [
                64.365493774414062,
                45.279075622558594
              ],
              [
                64.354469299316406,
                45.321468353271484
              ],
              [
                64.460479736328125,
                45.319931030273494
              ],
              [
                64.423133850097656,
                45.493587493896541
              ],
              [
                64.349899291992244,
                45.722686767578125
              ],
              [
                64.378128051757869,
                45.967105865478516
              ],
              [
                64.147254943847599,
                46.257926940917969
              ],
              [
                63.972957611084041,
                46.37042236328125
              ],
              [
                63.7978515625,
                46.698532104492244
              ],
              [
                63.781917572021428,
                46.817203521728516
              ],
              [
                63.821067810058707,
                46.84622955322277
              ],
              [
                64.323867797851676,
                46.711109161377067
              ],
              [
                64.426925659179688,
                46.709228515625057
              ],
              [
                64.930221557617131,
                46.522457122802848
              ],
              [
                64.854080200195426,
                46.389003753662109
              ],
              [
                64.887451171875114,
                46.152263641357536
              ],
              [
                64.879287719726676,
                45.975334167480582
              ],
              [
                64.859970092773494,
                45.82810211181652
              ],
              [
                64.839401245117301,
                45.790512084961051
              ],
              [
                64.768020629882869,
                45.319339752197379
              ],
              [
                64.785324096679688,
                45.285308837890568
              ],
              [
                64.752006530761776,
                45.243667602539176
              ],
              [
                64.761077880859375,
                45.16757965087902
              ],
              [
                64.833961486816406,
                45.115776062011719
              ],
              [
                64.808128356933707,
                45.099315643310604
              ],
              [
                64.824943542480412,
                45.056858062744254
              ],
              [
                64.799697875976619,
                45.053043365478629
              ],
              [
                64.847389221191463,
                45.001651763916016
              ],
              [
                64.771423339843807,
                44.981746673583928
              ],
              [
                64.763679504394645,
                44.948104858398438
              ],
              [
                64.880867004394531,
                44.916748046875114
              ],
              [
                64.847862243652344,
                44.879287719726562
              ],
              [
                64.741539001464957,
                44.868232727050781
              ],
              [
                64.609909057617244,
                44.827903747558707
              ],
              [
                64.609130859375057,
                44.806789398193473
              ],
              [
                64.670509338378906,
                44.797470092773438
              ],
              [
                64.679435729980469,
                44.708625793457088
              ],
              [
                64.72772216796875,
                44.682601928710938
              ],
              [
                64.737564086914176,
                44.454250335693416
              ],
              [
                64.671112060546932,
                44.2689208984375
              ],
              [
                64.718994140625057,
                43.668365478515682
              ],
              [
                64.672576904296875,
                43.651668548584041
              ],
              [
                64.664314270019645,
                43.647968292236328
              ],
              [
                64.645751953125057,
                43.642265319824332
              ],
              [
                64.638916015625057,
                43.639690399170036
              ]
            ]
          ]
        ]
      },
      "properties": {
        "name": "Zhalaganshskiy",
        "id": "Zhalaganshskiy",
        "datastat": "0/0/0",
        "dataImg": [
          "http://localhost:63342/map/green.svg?_ijt=d277mp04sbfulu08g6qou6kdag",
          "http://localhost:63342/map/red.svg?_ijt=d277mp04sbfulu08g6qou6kdag",
          "http://localhost:63342/map/yellow.svg?_ijt=d277mp04sbfulu08g6qou6kdag"
        ]
      }
    },
    {
      "type": "Feature",
      "geometry": {
        "type": "MultiPolygon",
        "coordinates": [
          [
            [
              [
                66.10693359375,
                42.362068176269645
              ],
              [
                66.107254028320256,
                42.365829467773494
              ],
              [
                66.107238769531364,
                42.36668777465826
              ],
              [
                66.106903076171875,
                42.388103485107536
              ],
              [
                66.106491088867131,
                42.414478302001953
              ],
              [
                66.106391906738338,
                42.421028137207145
              ],
              [
                66.106414794921932,
                42.423805236816463
              ],
              [
                66.106536865234375,
                42.439849853515682
              ],
              [
                66.106719970703125,
                42.46282958984375
              ],
              [
                66.1055908203125,
                42.524177551269645
              ],
              [
                66.10514068603527,
                42.548408508300895
              ],
              [
                66.104209899902344,
                42.590061187744197
              ],
              [
                66.103836059570312,
                42.610809326171989
              ],
              [
                66.103744506835994,
                42.625064849853516
              ],
              [
                66.514038085937614,
                42.870281219482536
              ],
              [
                66.425041198730469,
                43.267696380615291
              ],
              [
                66.392478942871151,
                43.310260772705135
              ],
              [
                66.773880004882812,
                43.41478347778326
              ],
              [
                66.797058105468807,
                43.729476928710881
              ],
              [
                66.805961608886719,
                43.846755981445426
              ],
              [
                66.869186401367301,
                43.89570236206049
              ],
              [
                66.856925964355526,
                43.967208862304744
              ],
              [
                66.936630249023438,
                44.069980621338004
              ],
              [
                67.041893005371094,
                44.188491821289119
              ],
              [
                67.206260681152287,
                44.292232513427848
              ],
              [
                67.344635009765682,
                44.300201416015625
              ],
              [
                67.399848937988395,
                44.381786346435604
              ],
              [
                67.471511840820369,
                44.379211425781307
              ],
              [
                67.492477416992244,
                44.411830902099553
              ],
              [
                67.53794097900402,
                44.385097503662223
              ],
              [
                67.592422485351619,
                44.391372680664062
              ],
              [
                67.580635070800895,
                44.329242706298771
              ],
              [
                67.687141418457031,
                44.254203796386719
              ],
              [
                67.748222351074276,
                44.268440246582145
              ],
              [
                67.863082885742244,
                44.222000122070312
              ],
              [
                67.865768432617301,
                44.188537597656364
              ],
              [
                67.980690002441406,
                44.087760925293026
              ],
              [
                68.255691528320256,
                43.946174621582031
              ],
              [
                68.18527984619152,
                43.895359039306641
              ],
              [
                68.146446228027344,
                43.917949676513729
              ],
              [
                68.085517883300895,
                43.899887084960994
              ],
              [
                68.034156799316463,
                43.860538482666072
              ],
              [
                68.055435180664062,
                43.838790893554688
              ],
              [
                68.084823608398438,
                43.783393859863338
              ],
              [
                68.073089599609432,
                43.675758361816406
              ],
              [
                68.030426025390568,
                43.660976409912109
              ],
              [
                67.931404113769645,
                43.723426818847656
              ],
              [
                67.932151794433707,
                43.565299987792969
              ],
              [
                67.836753845214901,
                43.494262695312614
              ],
              [
                67.844802856445426,
                43.460670471191463
              ],
              [
                67.8240966796875,
                43.378307342529297
              ],
              [
                67.722785949707031,
                43.357124328613395
              ],
              [
                67.752738952636719,
                43.260395050048828
              ],
              [
                67.795555114746151,
                43.279609680175838
              ],
              [
                67.77939605712902,
                43.342571258544865
              ],
              [
                67.834312438964957,
                43.365440368652401
              ],
              [
                67.823394775390682,
                43.320133209228516
              ],
              [
                67.881729125976619,
                43.322040557861328
              ],
              [
                67.863967895507812,
                43.268722534179688
              ],
              [
                67.902427673339957,
                43.200828552246094
              ],
              [
                67.973609924316406,
                43.214630126953239
              ],
              [
                67.969657897949276,
                43.181613922119141
              ],
              [
                67.871536254882926,
                43.135646820068359
              ],
              [
                67.539459228515739,
                43.013900756835938
              ],
              [
                67.271949768066463,
                42.941345214843864
              ],
              [
                67.02140045166027,
                42.802658081054801
              ],
              [
                66.73956298828125,
                42.592926025390625
              ],
              [
                66.598617553710938,
                42.657051086425838
              ],
              [
                66.282852172851619,
                42.414478302001953
              ],
              [
                66.194076538085938,
                42.346279144287166
              ],
              [
                66.10693359375,
                42.362068176269645
              ]
            ]
          ]
        ]
      },
      "properties": {
        "name": "Zhanakorganskiy",
        "id": "Zhanakorganskiy",
        "datastat": "0/0/0",
        "dataImg": [
          "http://localhost:63342/map/green.svg?_ijt=d277mp04sbfulu08g6qou6kdag",
          "http://localhost:63342/map/red.svg?_ijt=d277mp04sbfulu08g6qou6kdag",
          "http://localhost:63342/map/yellow.svg?_ijt=d277mp04sbfulu08g6qou6kdag"
        ]
      }
    }
  ]
}